defensics_pcap/__init__.py
defensics_pcap/__main__.py
defensics_pcap/start_cap.py
defensics_pcap/stop_cap.py
defensics_pcap-0.2.0.dist-info/LICENSE
defensics_pcap-0.2.0.dist-info/METADATA
defensics_pcap-0.2.0.dist-info/WHEEL
defensics_pcap-0.2.0.dist-info/entry_points.txt
defensics_pcap-0.2.0.dist-info/top_level.txt
defensics_pcap-0.2.0.dist-info/RECORD
