Metadata-Version: 2.1
Name: defensics-pcap
Version: 0.2.0
Summary: Unofficial Defensics Packet Capture Assistant Tool
Home-page: UNKNOWN
Author: Joshua Pereyda
License: UNKNOWN
Platform: UNKNOWN
Provides-Extra: dev
Requires-Dist: check-manifest ; extra == 'dev'
